Metadata-Version: 1.1
Name: SPPU-Scraper
Version: 0.1.1
Summary: A Scraper to fetch SPPU Engineering results.
Home-page: https://github.com/mohi7solanki/SPPU-Scraper
Author: Mohit Solanki
Author-email: mohitsolanki619@gmail.com
License: BSD license
Keywords: sppu_scraper,SPPU,Pune University
Platform: UNKNOWN
Classifier: Development Status :: 2 - Pre-Alpha
Classifier: Intended Audience :: End Users/Desktop
Classifier: License :: OSI Approved :: BSD License
Classifier: Natural Language :: English
Classifier: Programming Language :: Python :: 3
Classifier: Programming Language :: Python :: 3.4
Classifier: Programming Language :: Python :: 3.5
Classifier: Programming Language :: Python :: 3.6
